{
  "instagram": [
    {
      "id": "78443",
      "name": "moh solehuddin djkjhdysgsjag",
      "username": "mohsolehuddin",
      "password" : "soleh123",
      "gmail" : "soleh@gmail.com",
      "no" : "083000111000"
    },
    {
        "id": "774833",
        "name": "moh solehuddin",
        "username": "jarjit",
        "password": "19284673",
        "gmail": "solehddkhduyrh@gmail.com",
        "no": "0830000000"
      },
      {
        "id": "7803",
        "name": "moh solehuddin",
        "username": "jarjit botak",
        "password": "19284673",
        "gmail": "solehddkhduyrh@gmail.com",
        "no": "0838000000009"
      },
      {
      "id": "78443",
      "name": "moh solehuddin djkjhdysgsjag",
      "username": "mohsolehuddin",
      "password" : "soleh123",
      "gmail" : "soleh@gmail.com",
      "no" : "083000000000"
    }

  ]
}